{"cartridge":{"attributes":{"system":"NES-NTSC","crc":"1992D163","sha1":"FD88715A94381179834EEC298F78EC3B51FE43FE","dump":"ok","dumper":"bootgod","datedumped":"2006-10-10"},"board":[{"attributes":{"type":"NES-TEROM","pcb":"NES-TEROM-03","mapper":"4"},"prg":[{"attributes":{"name":"NES-A4-0 PRG","size":"32k","crc":"937ABA88","sha1":"8526B03424B9D90031DF07E85C21A5149B4F5EE8"}}],"chr":[{"attributes":{"name":"NES-A4-0 CHR","size":"32k","crc":"4AF6DED6","sha1":"8569C315245DEF6F72716A396181E57A3CFEF8B8"}}],"chip":[{"attributes":{"type":"MMC3B"}}],"cic":[{"attributes":{"type":"6113B1"}}]}],"game":[{"attributes":{"name":"Adventures of Lolo 2","altname":"","class":"Licensed","subclass":"","catalog":"NES-A4-USA","publisher":"HAL Laboratory","developer":"HAL Laboratory","region":"USA","players":"1","date":"1990-03"}}]}}