{"cartridge":{"attributes":{"system":"NES-NTSC","crc":"37BA3261","sha1":"4EF017EF87D84DC15B2C1F919E05066BE9559DC8","dump":"ok","dumper":"bootgod","datedumped":"2006-07-03"},"board":[{"attributes":{"type":"NES-SLROM","pcb":"NES-SLROM-06","mapper":"1"},"prg":[{"attributes":{"name":"NES-L3-0 PRG","size":"128k","crc":"153CDC91","sha1":"C9B669B579F548E9CDEE31869DA6E5ADE05349E5"}}],"chr":[{"attributes":{"name":"NES-L3-0 CHR","size":"128k","crc":"7ABBE901","sha1":"35C30B6794FF5000F3BAD29AC0298F99AA489F47"}}],"chip":[{"attributes":{"type":"MMC1B2"}}],"cic":[{"attributes":{"type":"6113B1"}}]}],"game":[{"attributes":{"name":"Back to the Future II & III","altname":"","class":"Licensed","subclass":"","catalog":"NES-L3-USA","publisher":"LJN","developer":"Beam Software","region":"USA","players":"1","date":"1990-09"}}]}}