{"cartridge":{"attributes":{"system":"NES-PAL-A","crc":"4BB9B840","sha1":"FCD91E2B0E7E5FEE9018F7C66B65640128A016D4","dump":"ok","dumper":"Kinopio","datedumped":"2011-06-26"},"board":[{"attributes":{"type":"NES-TLROM","pcb":"NES-TLROM-03","mapper":"4"},"prg":[{"attributes":{"name":"PAL-W6-0 PRG","size":"128k","crc":"C3AEC9FA","sha1":"9F5AD2BD13D6B3BA696662728F172F0B8B683F0E"}}],"chr":[{"attributes":{"name":"NES-W6-0 CHR","size":"128k","crc":"230349C9","sha1":"1527860F7C3005BC543696EAA72DD1A2C12A944C"}}],"chip":[{"attributes":{"type":"MMC3B"}}],"cic":[{"attributes":{"type":"3197A"}}]}],"game":[{"attributes":{"name":"Isolated Warrior","altname":"","class":"Licensed","subclass":"","catalog":"NES-W6-UKV","publisher":"Nintendo","developer":"KID","region":"United Kingdom","players":"1","date":"1991"}},{"attributes":{"name":"Isolated Warrior","altname":"","class":"Licensed","subclass":"","catalog":"NES-W6-ESP","publisher":"Nintendo","developer":"KID","region":"Spain","players":"1","date":"1991"}}]}}