{"cartridge":{"attributes":{"system":"NES-PAL-A","crc":"6720ABAC","sha1":"D3431F1B7B6B3389271BDD0A7066A5147C957370","dump":"ok","dumper":"Mark_K","datedumped":"2011-12-05"},"board":[{"attributes":{"type":"NES-TLROM","pcb":"NES-TLROM-03","mapper":"4"},"prg":[{"attributes":{"name":"PAL-56-0 PRG","size":"128k","crc":"32C4B857","sha1":"85E70F11357419D1BE23EEB76282449B190F9BAE"}}],"chr":[{"attributes":{"name":"PAL-56-0 CHR","size":"128k","crc":"E2917B27","sha1":"A7782703E45BBE7DFC9B59A7587AE1BAA50D6647"}}],"chip":[{"attributes":{"type":"MMC3C"}}],"cic":[{"attributes":{"type":"3197A"}}]}],"game":[{"attributes":{"name":"Bucky O'Hare","altname":"","class":"Licensed","subclass":"","catalog":"NES-56-UKV","publisher":"Palcom","developer":"Konami","region":"United Kingdom","players":"1","date":"1993-02-18"}},{"attributes":{"name":"Bucky O'Hare","altname":"","class":"Licensed","subclass":"","catalog":"NES-56-NOE","publisher":"Palcom","developer":"Konami","region":"Germany","players":"1","date":"1992-07-03"}},{"attributes":{"name":"Bucky O'Hare","altname":"","class":"Licensed","subclass":"","catalog":"NES-56-SCN","publisher":"Palcom","developer":"Konami","region":"Scandinavia","players":"1","date":"1993-02-18"}}]}}