{"cartridge":{"attributes":{"system":"NES-NTSC","crc":"99DDDB04","sha1":"3C011E4EA5EB7E93299347F8009E5BDF51E223EB","dump":"ok","dumper":"bootgod","datedumped":"2005-12-31"},"board":[{"attributes":{"type":"NES-TLROM","pcb":"NES-TLROM-03","mapper":"4"},"prg":[{"attributes":{"name":"NES-NI-0 PRG","size":"128k","crc":"9CB55B96","sha1":"437C326A4575895B9D7E567CAB4F70B2F44ED8DD"}}],"chr":[{"attributes":{"name":"NES-NI-0 CHR","size":"128k","crc":"A024AE14","sha1":"2E797A173161A61C14CE299E3C5A31C6029F2B50"}}],"chip":[{"attributes":{"type":"MMC3C"}}],"cic":[{"attributes":{"type":"6113B1"}}]}],"game":[{"attributes":{"name":"Tiny Toon Adventures","altname":"","class":"Licensed","subclass":"","catalog":"NES-NI-USA","publisher":"Konami","developer":"Konami","region":"USA","players":"2","date":"1991-12"}}]}}