{"cartridge":{"attributes":{"system":"NES-NTSC","revision":"A","crc":"CA594ACE","sha1":"FF5BCACF7417B4DE1C49F9E54C2905D91391455B","dump":"ok","dumper":"_zane","datedumped":"2007-12-30"},"board":[{"attributes":{"type":"NES-TSROM","pcb":"NES-TSROM-03","mapper":"4"},"prg":[{"attributes":{"name":"NES-MW-1 PRG","size":"128k","crc":"9ED99198","sha1":"F5920CFF6AF6EBD436FE7E019CC534C38B62501B"}}],"chr":[{"attributes":{"name":"NES-MW-0 CHR","size":"128k","crc":"F2BA1170","sha1":"D9976B677AD222B76FBDAF31713374E2F283D44E"}}],"wram":[{"attributes":{"size":"8k"}}],"chip":[{"attributes":{"type":"MMC3A"}}],"cic":[{"attributes":{"type":"6113B1"}}]}],"game":[{"attributes":{"name":"Super Mario Bros. 2","altname":"","class":"Licensed","subclass":"","catalog":"NES-MW-CAN","publisher":"Nintendo","developer":"Nintendo","region":"Canada","players":"2","date":"1988-11-15"}},{"attributes":{"name":"Super Mario Bros. 2","altname":"","class":"Licensed","subclass":"","catalog":"NES-MW-USA","publisher":"Nintendo","developer":"Nintendo","region":"USA","players":"2","date":"1988-10"}}]}}