{"cartridge":{"attributes":{"system":"NES-NTSC","crc":"D73AA04C","sha1":"445819CCCAAF2C48D1A2864D3CE53DED33839B08","dump":"ok","dumper":"bootgod","datedumped":"2006-03-18"},"board":[{"attributes":{"type":"NES-SLROM","pcb":"NES-SLROM-06","mapper":"1"},"prg":[{"attributes":{"name":"NES-CX-0 PRG","size":"128k","crc":"BDD55EA1","sha1":"6CFCE5B7659B3FC9409AD1861F061F26EB12F740"}}],"chr":[{"attributes":{"name":"NES-CX-0 CHR","size":"128k","crc":"59FEC08B","sha1":"5F31A4F882BC94F10A1D95636AEC2A49D138A0D3"}}],"chip":[{"attributes":{"type":"MMC1B3"}}],"cic":[{"attributes":{"type":"6113B1"}}]}],"game":[{"attributes":{"name":"Cool World","altname":"","class":"Licensed","subclass":"","catalog":"NES-CX-USA","publisher":"Ocean","developer":"Ocean","region":"USA","players":"1","date":"1993-06"}}]}}