{"cartridge":{"attributes":{"system":"NES-NTSC","revision":"A","crc":"EAF7ED72","sha1":"BE2F5DC8C5BA8EC1A344A71F9FB204750AF24FE7","dump":"ok","dumper":"polarz","datedumped":"2006-09-02"},"board":[{"attributes":{"type":"NES-SNROM","pcb":"NES-SNROM-03","mapper":"1"},"prg":[{"attributes":{"name":"NES-ZL-1 PRG","size":"128k","crc":"EAF7ED72","sha1":"BE2F5DC8C5BA8EC1A344A71F9FB204750AF24FE7"}}],"wram":[{"attributes":{"size":"8k","battery":"1"}}],"vram":[{"attributes":{"size":"8k"}}],"chip":[{"attributes":{"type":"MMC1A"}}],"cic":[{"attributes":{"type":"6113A"}}]}],"game":[{"attributes":{"name":"Legend of Zelda, The","altname":"","class":"Licensed","subclass":"","catalog":"NES-ZL-USA","publisher":"Nintendo","developer":"Nintendo","region":"USA","players":"1","date":"1987-07"}}]}}